Alkwaz/Alkwaz.py
Alkwaz/__init__.py
Alkwaz-1.1.1.dist-info/LICENSE
Alkwaz-1.1.1.dist-info/METADATA
Alkwaz-1.1.1.dist-info/WHEEL
Alkwaz-1.1.1.dist-info/top_level.txt
Alkwaz-1.1.1.dist-info/RECORD
